depwell/__init__.py
depwell-0.0.0.0.0.0.1a0.post1989452.dist-info/LICENSE
depwell-0.0.0.0.0.0.1a0.post1989452.dist-info/WHEEL
depwell-0.0.0.0.0.0.1a0.post1989452.dist-info/METADATA
depwell-0.0.0.0.0.0.1a0.post1989452.dist-info/RECORD
