Metadata-Version: 2.1
Name: depwell
Version: 0.0.0.0.0.0.1a0.post1989452
Summary: The pain
Author-email: labtopher <no@email.thanks>
Classifier: License :: OSI Approved :: The Unlicense (Unlicense)
